exactcover.cp38-win_amd64.pyd
exactcover-0.12.dist-info/METADATA
exactcover-0.12.dist-info/WHEEL
exactcover-0.12.dist-info/top_level.txt
exactcover-0.12.dist-info/RECORD
