Metadata-Version: 2.1
Name: exactcover
Version: 0.12
Summary: Exact cover solver
Home-page: http://github.com/Seemee/exactcover
Author: Kenneth Waters
Author-email: kwwaters@gmail.com
Maintainer: Symen Hovinga
Maintainer-email: itsfull@hotmail.com
License: UNKNOWN
Platform: UNKNOWN
Classifier: Development Status :: 2 - Pre-Alpha
Classifier: Programming Language :: Python :: 3
Classifier: License :: OSI Approved :: MIT License
Classifier: Operating System :: OS Independent
